MANIFEST.in
README.md
requirements.txt
setup.cfg
setup.py
tache/__init__.py
tache/_compat.py
tache/backend.py
tache/batch.py
tache/cached.py
tache/serializer.py
tache/shortid.py
tache/tache.py
tache/utils.py
tache.egg-info/PKG-INFO
tache.egg-info/SOURCES.txt
tache.egg-info/dependency_links.txt
tache.egg-info/requires.txt
tache.egg-info/top_level.txt