Metadata-Version: 1.1
Name: tache
Version: 0.2.0
Summary: A tag based invalidation caching library
Home-page: https://github.com/zhihu/tache
Author: wayhome
Author-email: y@zhihu.com
License: MIT
Platform: UNKNOWN
Classifier: Intended Audience :: Developers
Classifier: Programming Language :: Python :: 2
Classifier: Programming Language :: Python :: 3
Classifier: License :: OSI Approved :: MIT License
